harlequin_athena/__init__.py
harlequin_athena/adapter.py
harlequin_athena/cli_options.py
harlequin_athena/completions.py
harlequin_athena/functions.tsv
harlequin_athena/keywords.csv
harlequin_athena/py.typed
harlequin_athena-0.1.2.dist-info/METADATA
harlequin_athena-0.1.2.dist-info/WHEEL
harlequin_athena-0.1.2.dist-info/entry_points.txt
harlequin_athena-0.1.2.dist-info/licenses/LICENSE
harlequin_athena-0.1.2.dist-info/RECORD
