Metadata-Version: 2.4
Name: harlequin-athena
Version: 0.1.2
Summary: A Harlequin adapter for Amazon Athena.
License: MIT
License-File: LICENSE
Keywords: harlequin,athena,aws,sql,database,adapter
Author: Jacob Williams
Author-email: jacob@iakob.com
Requires-Python: >=3.10,<4.0
Classifier: Development Status :: 4 - Beta
Classifier: Intended Audience :: Developers
Classifier: License :: OSI Approved :: MIT License
Classifier: Programming Language :: Python :: 3
Classifier: Programming Language :: Python :: 3.10
Classifier: Programming Language :: Python :: 3.11
Classifier: Programming Language :: Python :: 3.12
Classifier: Programming Language :: Python :: 3.13
Classifier: Programming Language :: Python :: 3.14
Classifier: Topic :: Database
Classifier: Topic :: Software Development :: Libraries :: Python Modules
Requires-Dist: boto3 (>=1.34.0,<2.0.0)
Requires-Dist: harlequin (>=1.7,<3)
Requires-Dist: numpy (>=2.2.4,<3.0.0)
Requires-Dist: pyathena (>=3.0.0,<4.0.0)
Project-URL: Documentation, https://github.com/singlow/harlequin-athena
Project-URL: Homepage, https://harlequin.sh
Project-URL: Repository, https://github.com/singlow/harlequin-athena
